poisson_d/__init__.py
poisson_d/cli.py
poisson_d/commands.py
poisson_d/concurrent.py
poisson_d/poisson_d.py
poisson_d-0.5.0.dist-info/AUTHORS.rst
poisson_d-0.5.0.dist-info/LICENSE
poisson_d-0.5.0.dist-info/METADATA
poisson_d-0.5.0.dist-info/WHEEL
poisson_d-0.5.0.dist-info/top_level.txt
poisson_d-0.5.0.dist-info/RECORD
