Metadata-Version: 2.1
Name: poisson-d
Version: 0.5.0
Summary: poisson disk implementation in python
Author-email: Qi HU <hu.verrerie@gmail.com>
Maintainer-email: Qi HU <hu.verrerie@gmail.com>
License: MIT license
Project-URL: bugs, https://github.com/verrerie/poisson-d/issues
Project-URL: changelog, https://github.com/verrerie/poisson-d/blob/master/changelog.md
Project-URL: homepage, https://github.com/verrerie/poisson-d
License-File: LICENSE
License-File: AUTHORS.rst
Requires-Dist: typer
Requires-Dist: imageio ==2.36.0
Provides-Extra: dev
Requires-Dist: coverage ; extra == 'dev'
Requires-Dist: mypy ; extra == 'dev'
Requires-Dist: pytest ; extra == 'dev'
Requires-Dist: ruff ; extra == 'dev'
